captif_cpx_db/__init__.py
captif_cpx_db/alembic.ini
captif_cpx_db/migrations/README
captif_cpx_db/migrations/__init__.py
captif_cpx_db/migrations/env.py
captif_cpx_db/migrations/script.py.mako
captif_cpx_db/migrations/versions/3067faed075e_.py
captif_cpx_db/migrations/versions/bb1258b4093b_modify_schema_for_texture_results.py
captif_cpx_db/models.py
captif_cpx_db/version.py
captif_cpx_db-2.0.dist-info/LICENSE
captif_cpx_db-2.0.dist-info/METADATA
captif_cpx_db-2.0.dist-info/WHEEL
captif_cpx_db-2.0.dist-info/RECORD
