Metadata-Version: 2.1
Name: captif-cpx-db
Version: 2.0
Summary: 
Author: John Bull
Author-email: john.bull@nzta.govt.nz
Requires-Python: >=3.9,<4.0
Classifier: Programming Language :: Python :: 3
Classifier: Programming Language :: Python :: 3.9
Classifier: Programming Language :: Python :: 3.10
Classifier: Programming Language :: Python :: 3.11
Classifier: Programming Language :: Python :: 3.12
Requires-Dist: alembic (>=1.13.1,<2.0.0)
Requires-Dist: captif-db-config (>=0.13,<0.14)
Requires-Dist: shapely (>=2.0.1,<3.0.0)
Requires-Dist: sqlmodel (>=0.0.8,<0.0.9)
